{"cameraMode":{"drawMode":0,"name":"Shaded","section":"Shading Mode"},"sceneLighting":false,"audioPlay":false,"sceneViewState":{"m_AlwaysRefresh":true,"showFog":true,"showSkybox":false,"showFlares":true,"showImageEffects":true,"showParticleSystems":true,"showVisualEffectGraphs":true,"m_FxEnabled":true},"in2DMode":false,"pivot":{"x":601.0,"y":422.0,"z":0.0},"rotation":{"x":0.2393457293510437,"y":0.7077693343162537,"z":-0.2813091576099396,"w":0.6022078394889832},"size":734.3602905273438,"orthographic":false}